jinja2_arrow/__init__.py
jinja2_arrow-0.2.1.dist-info/WHEEL
jinja2_arrow-0.2.1.dist-info/METADATA
jinja2_arrow-0.2.1.dist-info/licenses/LICENSE
jinja2_arrow-0.2.1.dist-info/RECORD
