Metadata-Version: 2.1
Name: jinja2-arrow
Version: 0.2.1
License: BSD-3-Clause
Author-email: lesleslie <les@wedgwoodwebworks.com>
Requires-Python: >=3.12
Classifier: Development Status :: 4 - Beta
Classifier: License :: OSI Approved :: BSD License
Classifier: Operating System :: OS Independent
Classifier: Programming Language :: Python
Classifier: Programming Language :: Python :: 3.12
Classifier: Topic :: Internet :: WWW/HTTP :: Dynamic Content
Classifier: Typing :: Typed
Requires-Dist: arrow>=1.3.0
Requires-Dist: jinja2>=3.1.4
